netbox_firmware/__init__.py
netbox_firmware/choices.py
netbox_firmware/navigation.py
netbox_firmware/search.py
netbox_firmware/signals.py
netbox_firmware/template_content.py
netbox_firmware/urls.py
netbox_firmware/utils.py
netbox_firmware/version.py
netbox_firmware/api/__init__.py
netbox_firmware/api/serializers.py
netbox_firmware/api/urls.py
netbox_firmware/api/views.py
netbox_firmware/api/serializers_/__init__.py
netbox_firmware/api/serializers_/bios.py
netbox_firmware/api/serializers_/firmware.py
netbox_firmware/filtersets/__init__.py
netbox_firmware/filtersets/bios.py
netbox_firmware/filtersets/firmware.py
netbox_firmware/forms/__init__.py
netbox_firmware/forms/bulk_edit/__init__.py
netbox_firmware/forms/bulk_edit/bios.py
netbox_firmware/forms/bulk_edit/firmware.py
netbox_firmware/forms/bulk_import/__init__.py
netbox_firmware/forms/bulk_import/bios.py
netbox_firmware/forms/bulk_import/firmware.py
netbox_firmware/forms/filtersets/__init__.py
netbox_firmware/forms/filtersets/bios.py
netbox_firmware/forms/filtersets/firmware.py
netbox_firmware/forms/models/__init__.py
netbox_firmware/forms/models/bios.py
netbox_firmware/forms/models/firmware.py
netbox_firmware/graphql/__init__.py
netbox_firmware/graphql/filters.py
netbox_firmware/graphql/schema.py
netbox_firmware/graphql/types.py
netbox_firmware/migrations/0001_initial.py
netbox_firmware/migrations/0002_alter_firmware_options_and_more.py
netbox_firmware/migrations/0003_alter_firmware_options_alter_firmware_device_type_and_more.py
netbox_firmware/migrations/0004_firmware_manufacturer_and_more.py
netbox_firmware/migrations/0005_alter_firmware_manufacturer.py
netbox_firmware/migrations/0006_alter_bios_options_and_more.py
netbox_firmware/migrations/0007_alter_bios_manufacturer.py
netbox_firmware/migrations/__init__.py
netbox_firmware/models/__init__.py
netbox_firmware/models/bios.py
netbox_firmware/models/firmware.py
netbox_firmware/tables/__init__.py
netbox_firmware/tables/bios.py
netbox_firmware/tables/firmware.py
netbox_firmware-4.3.1.dist-info/METADATA
netbox_firmware-4.3.1.dist-info/WHEEL
netbox_firmware-4.3.1.dist-info/top_level.txt
netbox_firmware-4.3.1.dist-info/RECORD
