Metadata-Version: 2.4
Name: netbox_firmware
Version: 4.3.1
Summary: Firmware management in NetBox
Author-email: Bart Van der Biest <bart@zimmo.be>
Keywords: netbox,netbox-plugin,Firmware
Classifier: Programming Language :: Python :: 3
Classifier: License :: OSI Approved :: MIT License
Classifier: Operating System :: OS Independent
Requires-Python: >=3.10
